{
  "data": {
    "id": "0436adc8-9ec9-422c-9486-a44ce021eedf",
    "type": "open_call",
    "attributes": {
      "name": "Open call 1",
      "slug": "kutch-spencer-open-call-1",
      "description": "Voluptatem blanditiis autem. Iste voluptates rerum. Animi tempore iure. Inventore facere ad.",
      "ticket_size": "scaling",
      "instrument_type": "loan",
      "sdgs": [
        1,
        4,
        5
      ],
      "money_distribution": "Et dolorem assumenda. Praesentium magni totam. Dolorem minima et. Incidunt omnis error.",
      "impact_description": "Voluptas molestiae est. Omnis asperiores quia. Dolorem autem corrupti. Totam nemo laborum.",
      "closing_at": "2023-01-03T15:10:20.792Z",
      "language": "en"
    },
    "relationships": {
      "investor": {
        "data": {
          "id": "6618f883-0d83-4b35-a476-9ca3dcc669bb",
          "type": "investor"
        }
      }
    }
  }
}